journal/__init__.py
journal/journal.py
journalist-0.0.3.dist-info/DESCRIPTION.rst
journalist-0.0.3.dist-info/METADATA
journalist-0.0.3.dist-info/RECORD
journalist-0.0.3.dist-info/WHEEL
journalist-0.0.3.dist-info/entry_points.txt
journalist-0.0.3.dist-info/metadata.json
journalist-0.0.3.dist-info/top_level.txt
